aio_statsd/__init__.py
aio_statsd/client.py
aio_statsd/connection.py
aio_statsd/protocol.py
aio_statsd/transport_layer_protocol.py
aio_statsd/utlis.py
aio_statsd-0.2.9.dist-info/LICENSE
aio_statsd-0.2.9.dist-info/METADATA
aio_statsd-0.2.9.dist-info/WHEEL
aio_statsd-0.2.9.dist-info/RECORD
