Metadata-Version: 2.1
Name: aio-statsd
Version: 0.2.9
Summary: an asyncio-based client for send metric to StatsD, Graphite.carbon, TelegrafStatsD and DogStatsD.
Home-page: https://github.com/so1n/aiostatsd
License: MIT
Author: So1n
Author-email: qaz6803609@163.com
Requires-Python: >=3.6,<4.0
Classifier: License :: OSI Approved :: MIT License
Classifier: Programming Language :: Python :: 3
Classifier: Programming Language :: Python :: 3.6
Classifier: Programming Language :: Python :: 3.7
Classifier: Programming Language :: Python :: 3.8
Classifier: Programming Language :: Python :: 3.9
Classifier: Programming Language :: Python :: 3.10
Classifier: Programming Language :: Python :: 3.11
Project-URL: Repository, https://github.com/so1n/aiostatsd
